README.rst
setup.cfg
setup.py
pypete/__init__.py
pypete/pypete.py
pypete.egg-info/PKG-INFO
pypete.egg-info/SOURCES.txt
pypete.egg-info/dependency_links.txt
pypete.egg-info/entry_points.txt
pypete.egg-info/requires.txt
pypete.egg-info/top_level.txt