Metadata-Version: 1.0
Name: pypete
Version: 0.1
Summary: Pypete - Python Performance Tests
Home-page: https://github.com/Artimi/pypete
Author: Petr Šebek
Author-email: petrsebek1@gmail.com
License: MIT
Keywords: performance tests nose plugin
Platform: UNKNOWN
